{
  "execution_summary": {
    "total_gates": 9,
    "passed_gates": 0,
    "failed_gates": 9,
    "overall_score": 0.1111111111111111,
    "execution_time_ms": 16.85929298400879,
    "timestamp": "2025-08-27T20:53:34.505616"
  },
  "generation_results": {
    "generation_1": {
      "gates": 4,
      "passed": 0
    },
    "generation_2": {
      "gates": 0,
      "passed": 0
    },
    "generation_3": {
      "gates": 5,
      "passed": 0
    }
  },
  "research_analysis": {
    "total_opportunities": 2,
    "opportunities": [
      "Novel algorithmic approach suitable for academic publication",
      "Significant performance improvement over baselines"
    ],
    "novel_algorithms_detected": 1,
    "performance_breakthroughs": 1,
    "architectural_innovations": 0,
    "publication_readiness_score": 0.9500000000000001,
    "recommended_actions": [
      "Prepare comparative study with established VLM baselines",
      "Design controlled experiments measuring inference latency vs accuracy",
      "Create reproducible benchmark suite for academic validation",
      "Prepare open-source dataset and evaluation metrics"
    ]
  },
  "detailed_results": [
    {
      "gate_name": "code_compilation",
      "status": "failed",
      "execution_time_ms": 1.0852813720703125,
      "score": 0.0,
      "details": {
        "success": false,
        "error": "[Errno 2] No such file or directory: 'python'",
        "score": 0.0
      },
      "research_opportunities": [],
      "recommendations": [],
      "timestamp": "2025-08-27T20:53:34.489940"
    },
    {
      "gate_name": "basic_imports",
      "status": "failed",
      "execution_time_ms": 0.4532337188720703,
      "score": 0.0,
      "details": {
        "success": false,
        "error": "No module named 'fast_vlm_ondevice'",
        "score": 0.0
      },
      "research_opportunities": [],
      "recommendations": [],
      "timestamp": "2025-08-27T20:53:34.490656"
    },
    {
      "gate_name": "core_functionality",
      "status": "failed",
      "execution_time_ms": 0.36215782165527344,
      "score": 0.0,
      "details": {
        "success": false,
        "error": "No module named 'fast_vlm_ondevice'",
        "score": 0.0
      },
      "research_opportunities": [],
      "recommendations": [],
      "timestamp": "2025-08-27T20:53:34.491271"
    },
    {
      "gate_name": "minimal_tests",
      "status": "failed",
      "execution_time_ms": 1.0743141174316406,
      "score": 0.0,
      "details": {
        "success": false,
        "error": "[Errno 2] No such file or directory: 'python'",
        "score": 0.0
      },
      "research_opportunities": [],
      "recommendations": [],
      "timestamp": "2025-08-27T20:53:34.492532"
    },
    {
      "gate_name": "performance_benchmarks",
      "status": "failed",
      "execution_time_ms": 0.44608116149902344,
      "score": 0.0,
      "details": {
        "success": false,
        "error": "No module named 'fast_vlm_ondevice'",
        "score": 0.0
      },
      "research_opportunities": [],
      "recommendations": [],
      "timestamp": "2025-08-27T20:53:34.493216"
    },
    {
      "gate_name": "scalability_tests",
      "status": "failed",
      "execution_time_ms": 7.87353515625,
      "score": 0.0,
      "details": {
        "success": false,
        "error": "'return' outside function (<string>, line 4)",
        "score": 0.0
      },
      "research_opportunities": [],
      "recommendations": [],
      "timestamp": "2025-08-27T20:53:34.501227"
    },
    {
      "gate_name": "optimization_validation",
      "status": "failed",
      "execution_time_ms": 0.41556358337402344,
      "score": 0.5,
      "details": {
        "success": false,
        "error": "No module named 'fast_vlm_ondevice'",
        "score": 0.5
      },
      "research_opportunities": [],
      "recommendations": [],
      "timestamp": "2025-08-27T20:53:34.501951"
    },
    {
      "gate_name": "production_readiness",
      "status": "failed",
      "execution_time_ms": 0.34999847412109375,
      "score": 0.5,
      "details": {
        "success": false,
        "error": "No module named 'fast_vlm_ondevice'",
        "score": 0.5
      },
      "research_opportunities": [],
      "recommendations": [],
      "timestamp": "2025-08-27T20:53:34.502480"
    },
    {
      "gate_name": "deployment_automation",
      "status": "failed",
      "execution_time_ms": 1.0013580322265625,
      "score": 0.0,
      "details": {
        "success": false,
        "error": "[Errno 2] No such file or directory: 'python'",
        "score": 0.0
      },
      "research_opportunities": [],
      "recommendations": [],
      "timestamp": "2025-08-27T20:53:34.503626"
    }
  ],
  "recommendations": [],
  "next_actions": [
    "Fix 9 failed quality gates",
    "Prepare research publications from detected opportunities",
    "Focus on Generation 2 reliability improvements"
  ]
}